md410_common/__init__.py
md410_common/build_pdf.py
md410_common/constants.py
md410_common/emailer.py
md410_common/models.py
md410_common/mongo.py
md410_common/sqs.py
md410_common/test.py
md410_common-0.4.0.dist-info/METADATA
md410_common-0.4.0.dist-info/WHEEL
md410_common-0.4.0.dist-info/top_level.txt
md410_common-0.4.0.dist-info/RECORD
